__init__.py
models.py
context_manager/__init__.py
context_manager/__main__.py
context_manager/anthropic_client.py
context_manager/cli.py
context_manager/deepseek_client.py
context_manager/gemini_client.py
context_manager/openai_client.py
context_manager/storage.py
mcp_server/__init__.py
mcp_server/__main__.py
mcp_server/server.py
mcp_toolz-0.3.13.dist-info/licenses/LICENSE
mcp_toolz-0.3.13.dist-info/METADATA
mcp_toolz-0.3.13.dist-info/WHEEL
mcp_toolz-0.3.13.dist-info/entry_points.txt
mcp_toolz-0.3.13.dist-info/top_level.txt
mcp_toolz-0.3.13.dist-info/RECORD
