Metadata-Version: 2.4
Name: mcp-toolz
Version: 0.3.13
Summary: Save contexts and todos across Claude Code sessions, get feedback from ChatGPT, Claude, Gemini, and DeepSeek
Author-email: Taylor Leese <tleese22@gmail.com>
License-Expression: MIT
Project-URL: Homepage, https://github.com/taylorleese/mcp-toolz
Project-URL: Repository, https://github.com/taylorleese/mcp-toolz
Project-URL: Issues, https://github.com/taylorleese/mcp-toolz/issues
Project-URL: Documentation, https://github.com/taylorleese/mcp-toolz#readme
Keywords: mcp,model-context-protocol,claude-code,context-management,todo-persistence,ai-assistant,chatgpt,anthropic,gemini,deepseek
Classifier: Development Status :: 4 - Beta
Classifier: Intended Audience :: Developers
Classifier: Programming Language :: Python :: 3
Classifier: Programming Language :: Python :: 3.13
Classifier: Topic :: Software Development :: Libraries :: Python Modules
Classifier: Topic :: Scientific/Engineering :: Artificial Intelligence
Requires-Python: >=3.13
License-File: LICENSE
Requires-Dist: mcp==1.25.0
Requires-Dist: pydantic==2.12.5
Requires-Dist: openai==2.14.0
Requires-Dist: anthropic==0.75.0
Requires-Dist: google-generativeai==0.8.6
Requires-Dist: click==8.3.1
Requires-Dist: python-dotenv==1.2.1
Requires-Dist: aiosqlite==0.22.1
Requires-Dist: urllib3==2.6.3
Dynamic: license-file
